bankreport/.DS_Store
bankreport/__init__.py
bankreport/__main__.py
bankreport/cli.py
bankreport/templates.py
bankreport-0.1.6.dist-info/entry_points.txt
bankreport-0.1.6.dist-info/WHEEL
bankreport-0.1.6.dist-info/METADATA
bankreport-0.1.6.dist-info/RECORD
