Metadata-Version: 2.1
Name: bankreport
Version: 0.1.6
Summary: Parse and analyze csv files from online banking.
Home-page: https://github.com/heinrichhartmann/bankreport
Author: Heinrich Hartmann
Author-email: heinrich@heinrichhartmann.com
Requires-Python: >=3.8,<4.0
Classifier: Programming Language :: Python :: 3
Classifier: Programming Language :: Python :: 3.10
Classifier: Programming Language :: Python :: 3.8
Classifier: Programming Language :: Python :: 3.9
Requires-Dist: click (>=8.1.3,<9.0.0)
Requires-Dist: pandas (>=1.5.2,<2.0.0)
Project-URL: Repository, https://github.com/heinrichhartmann/bankreport
